encord/__init__.py
encord/_version.py
encord/api/__init__.py
encord/api/ml_endpoints.py
encord/client.py
encord/client_metadata_schema.py
encord/collection.py
encord/common/__init__.py
encord/common/bitmask_operations/__init__.py
encord/common/bitmask_operations/bitmask_operations.py
encord/common/bitmask_operations/bitmask_operations_numpy.py
encord/common/constants.py
encord/common/deprecated.py
encord/common/enum.py
encord/common/integer_range_set.py
encord/common/range_manager.py
encord/common/time_parser.py
encord/common/utils.py
encord/configs.py
encord/constants/__init__.py
encord/constants/enums.py
encord/constants/string_constants.py
encord/dataset.py
encord/exceptions.py
encord/filter_preset.py
encord/http/__init__.py
encord/http/bundle.py
encord/http/common.py
encord/http/constants.py
encord/http/error_utils.py
encord/http/limits.py
encord/http/querier.py
encord/http/query_methods.py
encord/http/request.py
encord/http/utils.py
encord/http/v2/__init__.py
encord/http/v2/api_client.py
encord/http/v2/error_utils.py
encord/http/v2/payloads.py
encord/http/v2/request_signer.py
encord/issues/issue_client.py
encord/metadata_schema.py
encord/ml_models_client.py
encord/objects/__init__.py
encord/objects/answers.py
encord/objects/attributes.py
encord/objects/bitmask.py
encord/objects/bundled_operations.py
encord/objects/classification.py
encord/objects/classification_instance.py
encord/objects/common.py
encord/objects/constants.py
encord/objects/coordinates.py
encord/objects/frames.py
encord/objects/html_node.py
encord/objects/internal_helpers.py
encord/objects/label_utils.py
encord/objects/metadata.py
encord/objects/ml_models.py
encord/objects/ontology_element.py
encord/objects/ontology_labels_impl.py
encord/objects/ontology_object.py
encord/objects/ontology_object_instance.py
encord/objects/ontology_structure.py
encord/objects/options.py
encord/objects/project.py
encord/objects/skeleton_template.py
encord/objects/spaces/annotation/base_annotation.py
encord-0.1.187.dist-info/WHEEL
encord-0.1.187.dist-info/METADATA
encord-0.1.187.dist-info/RECORD
