Metadata-Version: 2.3
Name: encord
Version: 0.1.187
Summary: Encord Python SDK Client
Keywords: encord
Author: Cord Technologies Limited
Author-email: Cord Technologies Limited <hello@encord.com>
License: Apache Software License
Classifier: Programming Language :: Python :: 3
Classifier: License :: OSI Approved :: Apache Software License
Classifier: Operating System :: OS Independent
Requires-Dist: python-dateutil>=2.8.2,<3.0.0
Requires-Dist: requests>=2.25.0,<3.0.0
Requires-Dist: cryptography>=43.0.0
Requires-Dist: tqdm>=4.32.1,<5.0.0
Requires-Dist: pydantic>=1.10.14
Requires-Dist: orjson>=2
Requires-Dist: pycocotools>=2.0.7,<3.0.0 ; extra == 'coco'
Requires-Dist: shapely>=2.0.4,<3.0.0 ; extra == 'coco'
Requires-Dist: opencv-python>=4.11.0.86,<5.0.0.0 ; extra == 'coco'
Requires-Dist: numpy>=1.24,<2.0.0 ; python_full_version < '3.12' and extra == 'coco'
Requires-Dist: numpy>=1.26,<2.0.0 ; python_full_version >= '3.12' and extra == 'coco'
Requires-Python: >=3.9
Project-URL: documentation, https://python.docs.encord.com/
Project-URL: repository, https://github.com/encord-team/encord-client-python
Provides-Extra: coco
